cpyrt/__init__.py
cpyrt/models.py
cpyrt/utils.py
cpyrt-0.1.0.dist-info/LICENSE
cpyrt-0.1.0.dist-info/WHEEL
cpyrt-0.1.0.dist-info/METADATA
cpyrt-0.1.0.dist-info/RECORD
